MANIFEST.in
README.rst
requirements.txt
setup.cfg
setup.py
djmicrosip_polizasautomaticas/__init__.py
djmicrosip_polizasautomaticas/__init__.pyc
djmicrosip_polizasautomaticas/autocomplete_light_registry.pyc
djmicrosip_polizasautomaticas/config.pyc
djmicrosip_polizasautomaticas/forms.pyc
djmicrosip_polizasautomaticas/models.pyc
djmicrosip_polizasautomaticas/urls.pyc
djmicrosip_polizasautomaticas/views.pyc
djmicrosip_polizasautomaticas.egg-info/PKG-INFO
djmicrosip_polizasautomaticas.egg-info/SOURCES.txt
djmicrosip_polizasautomaticas.egg-info/dependency_links.txt
djmicrosip_polizasautomaticas.egg-info/requires.txt
djmicrosip_polizasautomaticas.egg-info/top_level.txt
djmicrosip_polizasautomaticas/custom_db/__init__.py
djmicrosip_polizasautomaticas/custom_db/__init__.pyc
djmicrosip_polizasautomaticas/custom_db/compras/__init__.py
djmicrosip_polizasautomaticas/custom_db/compras/__init__.pyc
djmicrosip_polizasautomaticas/custom_db/compras/sql_queries.pyc
djmicrosip_polizasautomaticas/custom_db/contabilidad/__init__.py
djmicrosip_polizasautomaticas/custom_db/contabilidad/__init__.pyc
djmicrosip_polizasautomaticas/custom_db/contabilidad/procedures.pyc
djmicrosip_polizasautomaticas/custom_db/punto_de_venta/__init__.py
djmicrosip_polizasautomaticas/custom_db/punto_de_venta/__init__.pyc
djmicrosip_polizasautomaticas/custom_db/punto_de_venta/sql_queries.pyc
djmicrosip_polizasautomaticas/custom_db/ventas/__init__.py
djmicrosip_polizasautomaticas/custom_db/ventas/__init__.pyc
djmicrosip_polizasautomaticas/custom_db/ventas/sql_queries.pyc
djmicrosip_polizasautomaticas/static/djmicrosip_polizasautomaticas/js/log.js
djmicrosip_polizasautomaticas/static/djmicrosip_polizasautomaticas/js/tarea_preferencias.js
djmicrosip_polizasautomaticas/templates/djmicrosip_polizasautomaticas/base.html
djmicrosip_polizasautomaticas/templates/djmicrosip_polizasautomaticas/crea_anteriores.html
djmicrosip_polizasautomaticas/templates/djmicrosip_polizasautomaticas/index.html
djmicrosip_polizasautomaticas/templates/djmicrosip_polizasautomaticas/log.html
djmicrosip_polizasautomaticas/templates/djmicrosip_polizasautomaticas/preferencias.html
djmicrosip_polizasautomaticas/templates/djmicrosip_polizasautomaticas/recalculo.html
